{
  "QuestInfo": {
    "_dirType": "sub",
    "name": {
      "_dirType": "string",
      "_value": "[維多利亞島] 沙拉的材料"
    },
    "1": {
      "_dirType": "string",
      "_value": "卡蜜拉為了生病的瑪亞想要製作對健康有益的綠色菇菇沙拉而請求尋找材料.\r\n\r\n找到綠菇菇傘10個, 蛋黃色傘10個後交給卡蜜拉.\r\n"
    },
    "2": {
      "_dirType": "string",
      "_value": "為了生病的瑪亞找到沙拉材料後拿給卡蜜拉了.\r\n"
    },
    "demandSummary": {
      "_dirType": "string",
      "_value": "#questorder1##i4033021:# #t4033021:# #c4033021# / 10\r\n#questorder1##i4000012:# #t4000012:# #c4000012# / 10\r\n"
    },
    "rewardSummary": {
      "_dirType": "string",
      "_value": "#Wbasic#\r\n#fUI/UIWindow2.img/QuestIcon/8/0# 621\r\n能以'為了瑪亞準備的沙拉' 任務進行\r\n"
    },
    "0": {
      "_dirType": "string",
      "_value": "聽說弓箭手村的卡蜜拉有什麼事情要拜託..."
    },
    "area": {
      "_dirType": "int",
      "_value": "30"
    },
    "startNavi": {
      "_dirType": "int",
      "_value": "1"
    },
    "targetMapID": {
      "_dirType": "int",
      "_value": "100020000"
    },
    "targetPN": {
      "_dirType": "string",
      "_value": "west00"
    },
    "returnType": {
      "_dirType": "int",
      "_value": "1"
    },
    "returnMapID": {
      "_dirType": "int",
      "_value": "100000000"
    },
    "returnPN": {
      "_dirType": "string",
      "_value": "1012108"
    },
    "blocked": {
      "_dirType": "int",
      "_value": "1"
    },
    "reward": {
      "_dirType": "sub",
      "exp": {
        "_dirType": "int",
        "_value": "621"
      },
      "item": {
        "_dirType": "sub"
      },
      "explain": {
        "_dirType": "sub",
        "summaryDemand": {
          "_dirType": "sub",
          "order": {
            "_dirType": "int",
            "_value": "1"
          }
        }
      }
    },
    "parent": {
      "_dirType": "string",
      "_value": "卡蜜拉的料理百書"
    }
  },
  "Check": {
    "_dirType": "sub",
    "0": {
      "_dirType": "sub",
      "npc": {
        "_dirType": "int",
        "_value": "1012108"
      },
      "lvmin": {
        "_dirType": "int",
        "_value": "10"
      },
      "subJobFlags": {
        "_dirType": "int",
        "_value": "1037"
      },
      "job": {
        "_dirType": "sub",
        "0": {
          "_dirType": "int",
          "_value": "0"
        },
        "1": {
          "_dirType": "int",
          "_value": "100"
        },
        "2": {
          "_dirType": "int",
          "_value": "110"
        },
        "3": {
          "_dirType": "int",
          "_value": "120"
        },
        "4": {
          "_dirType": "int",
          "_value": "130"
        },
        "5": {
          "_dirType": "int",
          "_value": "111"
        },
        "6": {
          "_dirType": "int",
          "_value": "121"
        },
        "7": {
          "_dirType": "int",
          "_value": "131"
        },
        "8": {
          "_dirType": "int",
          "_value": "112"
        },
        "9": {
          "_dirType": "int",
          "_value": "122"
        },
        "10": {
          "_dirType": "int",
          "_value": "132"
        },
        "11": {
          "_dirType": "int",
          "_value": "113"
        },
        "12": {
          "_dirType": "int",
          "_value": "123"
        },
        "13": {
          "_dirType": "int",
          "_value": "133"
        },
        "14": {
          "_dirType": "int",
          "_value": "200"
        },
        "15": {
          "_dirType": "int",
          "_value": "210"
        },
        "16": {
          "_dirType": "int",
          "_value": "220"
        },
        "17": {
          "_dirType": "int",
          "_value": "230"
        },
        "18": {
          "_dirType": "int",
          "_value": "211"
        },
        "19": {
          "_dirType": "int",
          "_value": "221"
        },
        "20": {
          "_dirType": "int",
          "_value": "231"
        },
        "21": {
          "_dirType": "int",
          "_value": "212"
        },
        "22": {
          "_dirType": "int",
          "_value": "222"
        },
        "23": {
          "_dirType": "int",
          "_value": "232"
        },
        "24": {
          "_dirType": "int",
          "_value": "213"
        },
        "25": {
          "_dirType": "int",
          "_value": "223"
        },
        "26": {
          "_dirType": "int",
          "_value": "233"
        },
        "27": {
          "_dirType": "int",
          "_value": "300"
        },
        "28": {
          "_dirType": "int",
          "_value": "301"
        },
        "29": {
          "_dirType": "int",
          "_value": "310"
        },
        "30": {
          "_dirType": "int",
          "_value": "320"
        },
        "31": {
          "_dirType": "int",
          "_value": "330"
        },
        "32": {
          "_dirType": "int",
          "_value": "311"
        },
        "33": {
          "_dirType": "int",
          "_value": "321"
        },
        "34": {
          "_dirType": "int",
          "_value": "331"
        },
        "35": {
          "_dirType": "int",
          "_value": "312"
        },
        "36": {
          "_dirType": "int",
          "_value": "322"
        },
        "37": {
          "_dirType": "int",
          "_value": "332"
        },
        "38": {
          "_dirType": "int",
          "_value": "313"
        },
        "39": {
          "_dirType": "int",
          "_value": "323"
        },
        "40": {
          "_dirType": "int",
          "_value": "333"
        },
        "41": {
          "_dirType": "int",
          "_value": "400"
        },
        "42": {
          "_dirType": "int",
          "_value": "410"
        },
        "43": {
          "_dirType": "int",
          "_value": "420"
        },
        "44": {
          "_dirType": "int",
          "_value": "430"
        },
        "45": {
          "_dirType": "int",
          "_value": "411"
        },
        "46": {
          "_dirType": "int",
          "_value": "421"
        },
        "47": {
          "_dirType": "int",
          "_value": "431"
        },
        "48": {
          "_dirType": "int",
          "_value": "412"
        },
        "49": {
          "_dirType": "int",
          "_value": "422"
        },
        "50": {
          "_dirType": "int",
          "_value": "432"
        },
        "51": {
          "_dirType": "int",
          "_value": "413"
        },
        "52": {
          "_dirType": "int",
          "_value": "423"
        },
        "53": {
          "_dirType": "int",
          "_value": "433"
        },
        "54": {
          "_dirType": "int",
          "_value": "434"
        },
        "55": {
          "_dirType": "int",
          "_value": "435"
        },
        "56": {
          "_dirType": "int",
          "_value": "500"
        },
        "57": {
          "_dirType": "int",
          "_value": "501"
        },
        "58": {
          "_dirType": "int",
          "_value": "510"
        },
        "59": {
          "_dirType": "int",
          "_value": "520"
        },
        "60": {
          "_dirType": "int",
          "_value": "530"
        },
        "61": {
          "_dirType": "int",
          "_value": "511"
        },
        "62": {
          "_dirType": "int",
          "_value": "521"
        },
        "63": {
          "_dirType": "int",
          "_value": "531"
        },
        "64": {
          "_dirType": "int",
          "_value": "512"
        },
        "65": {
          "_dirType": "int",
          "_value": "522"
        },
        "66": {
          "_dirType": "int",
          "_value": "532"
        },
        "67": {
          "_dirType": "int",
          "_value": "513"
        },
        "68": {
          "_dirType": "int",
          "_value": "523"
        },
        "69": {
          "_dirType": "int",
          "_value": "533"
        },
        "70": {
          "_dirType": "int",
          "_value": "13100"
        },
        "71": {
          "_dirType": "int",
          "_value": "13500"
        }
      },
      "job_TW": {
        "_dirType": "sub",
        "0": {
          "_dirType": "int",
          "_value": "508"
        },
        "1": {
          "_dirType": "int",
          "_value": "570"
        },
        "2": {
          "_dirType": "int",
          "_value": "571"
        },
        "3": {
          "_dirType": "int",
          "_value": "572"
        },
        "4": {
          "_dirType": "int",
          "_value": "573"
        }
      }
    },
    "1": {
      "_dirType": "sub",
      "npc": {
        "_dirType": "int",
        "_value": "1012108"
      },
      "order": {
        "_dirType": "int",
        "_value": "1"
      },
      "item": {
        "_dirType": "sub",
        "0": {
          "_dirType": "sub",
          "id": {
            "_dirType": "int",
            "_value": "4033021"
          },
          "count": {
            "_dirType": "int",
            "_value": "10"
          },
          "order": {
            "_dirType": "int",
            "_value": "1"
          }
        },
        "1": {
          "_dirType": "sub",
          "id": {
            "_dirType": "int",
            "_value": "4000012"
          },
          "count": {
            "_dirType": "int",
            "_value": "10"
          },
          "order": {
            "_dirType": "int",
            "_value": "1"
          }
        }
      }
    }
  },
  "Act": {
    "_dirType": "sub",
    "0": {
      "_dirType": "sub",
      "transferField": {
        "_dirType": "int",
        "_value": "999999999"
      }
    },
    "1": {
      "_dirType": "sub",
      "exp": {
        "_dirType": "int",
        "_value": "621"
      },
      "item": {
        "_dirType": "sub",
        "0": {
          "_dirType": "sub",
          "id": {
            "_dirType": "int",
            "_value": "4033021"
          },
          "count": {
            "_dirType": "int",
            "_value": "-10"
          },
          "potentialGrade": {
            "_dirType": "string",
            "_value": "正常"
          }
        },
        "1": {
          "_dirType": "sub",
          "id": {
            "_dirType": "int",
            "_value": "4000012"
          },
          "count": {
            "_dirType": "int",
            "_value": "-10"
          },
          "potentialGrade": {
            "_dirType": "string",
            "_value": "正常"
          }
        }
      },
      "transferField": {
        "_dirType": "int",
        "_value": "999999999"
      }
    }
  },
  "Say": {
    "_dirType": "sub",
    "0": {
      "_dirType": "sub",
      "0": {
        "_dirType": "string",
        "_value": "你是誰呢? 啊~ 您好. 是赫麗娜所說的那位啊. 怎麼辦? 現在無法介紹村莊..."
      },
      "1": {
        "_dirType": "string",
        "_value": "瑪亞生病了... 雖然不好意思, 不過可以幫幫我嗎?"
      },
      "stop": {
        "_dirType": "sub"
      },
      "yes": {
        "_dirType": "sub",
        "0": {
          "_dirType": "string",
          "_value": "是個親切的人~ 吃下新鮮的沙拉瑪亞也可以恢復精神. 請尋找綠菇菇傘 10個, 綠菇菇黃彤彤的菇菇傘10個~ 去#m100020000#看看應該就可以找到."
        }
      },
      "no": {
        "_dirType": "sub",
        "0": {
          "_dirType": "string",
          "_value": "有事情在忙嗎? 是不是初次見面就太煩你了呢...?"
        }
      }
    },
    "1": {
      "_dirType": "sub",
      "0": {
        "_dirType": "string",
        "_value": "真的有找到新鮮的材料, #h0#. 用這些材料要趕緊做沙拉了. 可以稍等一下嗎?"
      },
      "yes": {
        "_dirType": "sub",
        "0": {
          "_dirType": "string",
          "_value": "趕緊製作完後拿給瑪亞."
        }
      },
      "stop": {
        "_dirType": "sub",
        "item": {
          "_dirType": "sub",
          "0": {
            "_dirType": "string",
            "_value": "沙拉材料可以從綠色菇菇取得, 去#m100020000#看看應該就可以找到."
          }
        }
      }
    }
  }
}
