{
  "QuestInfo": {
    "_dirType": "sub",
    "name": {
      "_dirType": "string",
      "_value": "[楓之谷世界的冒險家] 新的推測"
    },
    "parent": {
      "_dirType": "string",
      "_value": "極致的試煉"
    },
    "order": {
      "_dirType": "int",
      "_value": "5"
    },
    "1": {
      "_dirType": "string",
      "_value": "#p2022003#的話中有一些很奇怪的地方！看來去問#b#p2020010##k好了~\\n\\n#t4161027##b#c4161027#/1#k"
    },
    "2": {
      "_dirType": "string",
      "_value": "#p2020010#說，#p2022003#過去曾經是人類，說還是需要留意他所說的話~"
    },
    "blocked": {
      "_dirType": "int",
      "_value": "1"
    },
    "area": {
      "_dirType": "int",
      "_value": "77"
    },
    "category": {
      "_dirType": "string",
      "_value": "0|2"
    },
    "reward": {
      "_dirType": "sub",
      "exp": {
        "_dirType": "int",
        "_value": "100000"
      },
      "item": {
        "_dirType": "sub"
      },
      "explain": {
        "_dirType": "sub",
        "summaryDemand": {
          "_dirType": "sub",
          "order": {
            "_dirType": "int",
            "_value": "1"
          }
        }
      }
    }
  },
  "Check": {
    "_dirType": "sub",
    "0": {
      "_dirType": "sub",
      "npc": {
        "_dirType": "int",
        "_value": "2022003"
      },
      "lvmin": {
        "_dirType": "int",
        "_value": "120"
      },
      "quest": {
        "_dirType": "sub",
        "0": {
          "_dirType": "sub",
          "id": {
            "_dirType": "int",
            "_value": "6103"
          },
          "state": {
            "_dirType": "int",
            "_value": "2"
          }
        }
      },
      "job": {
        "_dirType": "sub",
        "0": {
          "_dirType": "int",
          "_value": "312"
        },
        "1": {
          "_dirType": "int",
          "_value": "322"
        }
      },
      "job_TW": {
        "_dirType": "sub"
      }
    },
    "1": {
      "_dirType": "sub",
      "npc": {
        "_dirType": "int",
        "_value": "2020010"
      },
      "order": {
        "_dirType": "int",
        "_value": "1"
      },
      "item": {
        "_dirType": "sub",
        "0": {
          "_dirType": "sub",
          "id": {
            "_dirType": "int",
            "_value": "4161027"
          },
          "count": {
            "_dirType": "int",
            "_value": "1"
          },
          "order": {
            "_dirType": "int",
            "_value": "1"
          }
        }
      }
    }
  },
  "Act": {
    "_dirType": "sub",
    "0": {
      "_dirType": "sub",
      "item": {
        "_dirType": "sub",
        "0": {
          "_dirType": "sub",
          "id": {
            "_dirType": "int",
            "_value": "4161027"
          },
          "count": {
            "_dirType": "int",
            "_value": "1"
          },
          "potentialGrade": {
            "_dirType": "string",
            "_value": "一般"
          }
        }
      }
    },
    "1": {
      "_dirType": "sub",
      "exp": {
        "_dirType": "int",
        "_value": "100000"
      },
      "item": {
        "_dirType": "sub",
        "0": {
          "_dirType": "sub",
          "id": {
            "_dirType": "int",
            "_value": "4161027"
          },
          "count": {
            "_dirType": "int",
            "_value": "-1"
          },
          "potentialGrade": {
            "_dirType": "string",
            "_value": "一般"
          }
        }
      }
    }
  },
  "Say": {
    "_dirType": "sub",
    "0": {
      "_dirType": "sub",
      "ask": {
        "_dirType": "int",
        "_value": "1"
      },
      "0": {
        "_dirType": "string",
        "_value": "果然！果然！果然是這樣啊…這就是傳說中的東西啊！你應該不知道吧！知道關於這本書的那個人...\\n\\r#L0##b難道你知道嗎？#k"
      },
      "1": {
        "_dirType": "string",
        "_value": "哈哈哈~#p2022003#怎麼會知道呢！不知道！絕對不知道！沒有人知道！"
      },
      "stop": {
        "_dirType": "sub",
        "0": {
          "_dirType": "sub",
          "answer": {
            "_dirType": "int",
            "_value": "1"
          }
        }
      },
      "yes": {
        "_dirType": "sub",
        "0": {
          "_dirType": "string",
          "_value": "沒有活著的人了解關於那本書的內容！絕對！哈哈哈！我不需要什麼書...你把它拿去吧！"
        }
      },
      "no": {
        "_dirType": "sub",
        "0": {
          "_dirType": "string",
          "_value": "沒有人會知道!任何人！你也是！就算是#p2020010#也是！哈哈哈！"
        }
      }
    },
    "1": {
      "_dirType": "sub",
      "0": {
        "_dirType": "string",
        "_value": "#p2022003#有說過這樣的話嗎？真的有意思...雖然說他脾氣乖僻，但#p2022003#之前畢竟是個人類，而且還是知識淵博的人物。他所說的話雖然心存惡意，但有時卻蘊涵即為賢明的指示，他所說的話可不能隨便忽略掉..."
      },
      "yes": {
        "_dirType": "sub",
        "0": {
          "_dirType": "string",
          "_value": "我得好好思考#p2022003#所說的話，請你稍等一下！"
        }
      },
      "stop": {
        "_dirType": "sub",
        "npc": {
          "_dirType": "sub",
          "0": {
            "_dirType": "string",
            "_value": "告訴#p2020010#...說他吵死人了！長老們的聲音怎麼都這麼大啊？吵死人了~"
          }
        },
        "item": {
          "_dirType": "sub",
          "0": {
            "_dirType": "string",
            "_value": "你有去找過#b#p2022003##k嗎？可是書呢？你把書放在哪裡啊？"
          }
        }
      },
      "lost": {
        "_dirType": "sub",
        "0": {
          "_dirType": "string",
          "_value": "呵呵呵~你遺失的東西就是這個嗎？我有點不想給你耶~"
        }
      }
    }
  }
}
